pybirthdayspackage/__init__.py
pybirthdayspackage/__main__.py
pybirthdayspackage/pybirthdays.py
pybirthdayspackage-1.0.2.dist-info/METADATA
pybirthdayspackage-1.0.2.dist-info/WHEEL
pybirthdayspackage-1.0.2.dist-info/entry_points.txt
pybirthdayspackage-1.0.2.dist-info/licenses/LICENSE
pybirthdayspackage-1.0.2.dist-info/RECORD
