Metadata-Version: 2.1
Name: pybirthdayspackage
Version: 1.0.2
Summary: A package that shows celebrities' birthdays
Project-URL: homepage, https://github.com/software-students-fall2022/python-package-exercise-project-3-team-15/
Author: Grace Zhang, Ishana Goyal, Laura Mazoni, Mark Chen
License-File: LICENSE
Classifier: License :: OSI Approved :: MIT License
Classifier: Operating System :: OS Independent
Classifier: Programming Language :: Python :: 3.7
Requires-Python: >=3.7
